wf_airtable_api_client/__init__.py
wf_airtable_api_client/api/__init__.py
wf_airtable_api_client/api/client.py
wf_airtable_api_client/const.py
wf_airtable_api_client/models/__init__.py
wf_airtable_api_client/models/auto_response_email_template.py
wf_airtable_api_client/models/base_model.py
wf_airtable_api_client/models/contact_info.py
wf_airtable_api_client/models/educators.py
wf_airtable_api_client/models/educators_schools.py
wf_airtable_api_client/models/geo_area_contacts.py
wf_airtable_api_client/models/geo_area_target_communities.py
wf_airtable_api_client/models/geo_areas.py
wf_airtable_api_client/models/guides_schools.py
wf_airtable_api_client/models/hubs.py
wf_airtable_api_client/models/languages.py
wf_airtable_api_client/models/montessori_certifications.py
wf_airtable_api_client/models/partners.py
wf_airtable_api_client/models/pods.py
wf_airtable_api_client/models/response.py
wf_airtable_api_client/models/schools.py
wf_airtable_api_client/models/ssj_fillout_get_involved.py
wf_airtable_api_client/models/ssj_typeform_start_a_school.py
wf_airtable_api_client/models/target_communities.py
wf_airtable_api_client/models/utils.py
wf_airtable_api_client-1.6.0.dist-info/LICENSE
wf_airtable_api_client-1.6.0.dist-info/METADATA
wf_airtable_api_client-1.6.0.dist-info/WHEEL
wf_airtable_api_client-1.6.0.dist-info/RECORD
