Metadata-Version: 2.1
Name: wf-airtable-api-client
Version: 1.6.0
Summary: WF Airtable API client
License: MIT
Author: Benjamin Jaffe-Talberg
Author-email: ben.talberg@gmail.com
Requires-Python: >=3.9,<4.0
Classifier: License :: OSI Approved :: MIT License
Classifier: Programming Language :: Python :: 3
Classifier: Programming Language :: Python :: 3.9
Classifier: Programming Language :: Python :: 3.10
Classifier: Programming Language :: Python :: 3.11
Classifier: Programming Language :: Python :: 3.12
Requires-Dist: requests (>=2.31.0,<3.0.0)
